{"Hm_lvt_9026e0124320144488a739be44652df7":"1771046401313|1739508841","idleinfinity.equip.scroll2259":"0","idleinfinity.login":"{\"name\":[\"RasdGch\",\"RasdSky\",\"xiaohua1\",\"niu2\",\"yaodui\",\"niu1\",\"yaodui2\",\"yaodui3\",\"15365261391\",\"w596931907\"],\"pwd\":[\"123456\",\"123456\",\"123456\",\"123456\",\"123456\",\"123456\",\"123456\",\"123456\",\"zxc123\",\"596931907\"],\"remember\":true}","idleinfinity.style":"0","panel-filter-mybag":"+3 骷髅法师","idleinfinity.equip.scroll2263":"0","idleinfinity.equip.scroll2268":"400"}