{"idleinfinity.equip.scroll4063":"439","idleinfinity.equip.scroll3969":"100","idleinfinity.chat.count":"0","idleinfinity.equip.scroll2263":"400","idleinfinity.equip.scroll3974":"100","idleinfinity.equip.scroll2287":"200","idleinfinity.equip.scroll2274":"383","idleinfinity.equip.scroll3972":"0","idleinfinity.equip.scroll3968":"0","idleinfinity.equip.scroll3979":"200","idleinfinity.equip.scroll4060":"300","idleinfinity.style":"0","idleinfinity.equip.scroll4061":"1151","idleinfinity.equip.scroll2278":"249","idleinfinity.equip.scroll4059":"249","Hm_lvt_9026e0124320144488a739be44652df7":"1771553458185|1739508841","idleinfinity.equip.scroll3970":"0","idleinfinity.equip.scroll4069":"700","idleinfinity.equip.scroll3976":"200","idleinfinity.equip.scroll2298":"0","idleinfinity.equip.scroll4067":"300","idleinfinity.equip.scroll3975":"0","idleinfinity.equip.scroll3978":"400","idleinfinity.equip.scroll4031":"1173","idleinfinity.equip.scroll4028":"461","idleinfinity.equip.scroll2259":"414","idleinfinity.equip.scroll3971":"100","idleinfinity.equip.scroll2268":"17","idleinfinity.equip.scroll2283":"100","idleinfinity.equip.scroll4027":"183","idleinfinity.equip.scroll4070":"1300","idleinfinity.equip.scroll4034":"0","idleinfinity.equip.scroll2272":"230","idleinfinity.equip.scroll4038":"100","idleinfinity.equip.scroll3981":"181"}