[
  {
    "死灵": [
      {
        "Lv": {
          "min": 1,
          "max": 10
        },
        "主手": "死灵[1-10]级主手",
        "副手": "死灵[1-10]级副手",
        "头盔": "死灵[1-10]级头盔",
        "护符": "死灵[1-10]级护符",
        "戒指1": "死灵[1-10]级戒指1",
        "戒指2": "死灵[1-10]级戒指2",
        "衣服": "死灵[1-10]级衣服",
        "腰带": "死灵[1-10]级腰带",
        "手套": "死灵[1-10]级手套",
        "靴子": "死灵[1-10]级靴子"
      },
      {
        "Lv": {
          "min": 10,
          "max": 23
        },
        "主手": "死灵[11-23]级主手",
        "副手": "死灵[11-23]级副手",
        "头盔": "死灵[11-23]级头盔",
        "护符": "死灵[11-23]级护符",
        "戒指1": "死灵[11-23]级戒指1",
        "戒指2": "死灵[11-23]级戒指2",
        "衣服": "死灵[11-23]级衣服",
        "腰带": "死灵[11-23]级腰带",
        "手套": "死灵[11-23]级手套",
        "靴子": "死灵[11-23]级靴子"
      }
    ],
    "武僧": [
      {
        "Lv": {
          "min": 1,
          "max": 34
        },
        "主手": "武僧[1-34]级主手",
        "副手": "武僧[1-34]级副手",
        "头盔": "武僧[1-34]级头盔",
        "护符": "武僧[1-34]级护符",
        "戒指1": "武僧[1-34]级戒指1",
        "戒指2": "武僧[1-34]级戒指2",
        "衣服": "武僧[1-34]级衣服",
        "腰带": "武僧[1-34]级腰带",
        "手套": "武僧[1-34]级手套",
        "靴子": "武僧[1-34]级靴子"
      },
      {
        "Lv": {
          "min": 34,
          "max": 66
        },
        "主手": "武僧[34-66]级主手",
        "副手": "武僧[34-66]级副手",
        "头盔": "武僧[34-66]级头盔",
        "护符": "武僧[34-66]级护符",
        "戒指1": "武僧[34-66]级戒指1",
        "戒指2": "武僧[34-66]级戒指2",
        "衣服": "武僧[34-66]级衣服",
        "腰带": "武僧[34-66]级腰带",
        "手套": "武僧[34-66]级手套",
        "靴子": "武僧[34-66]级靴子"
      }
    ]
  }
]